spotify_ws-1.1.1.dist-info/licenses/LICENSE
spotifyws/__init__.py
spotifyws/config.py
spotifyws/logger.py
spotifyws/sec.py
spotifyws/spotify.py
spotifyws/utils.py
spotifyws/ws.py
spotify_ws-1.1.1.dist-info/METADATA
spotify_ws-1.1.1.dist-info/WHEEL
spotify_ws-1.1.1.dist-info/top_level.txt
spotify_ws-1.1.1.dist-info/RECORD
