Metadata-Version: 2.4
Name: spotify-ws
Version: 1.1.1
Summary: A python wrapper for Spotify WebSockets
Author-email: Jacopo <jacopo.degattis@gmail.com>
License: GNU General Public License v3.0
Project-URL: Homepage, https://github.com/jacopo-degattis/spotifyws
Project-URL: Download, https://github.com/jacopo-degattis/spotifyws/archive/refs/tags/v1.1.1.tar.gz
Classifier: Development Status :: 3 - Alpha
Classifier: Intended Audience :: Developers
Classifier: Topic :: Software Development :: Build Tools
Classifier: License :: OSI Approved :: MIT License
Classifier: Programming Language :: Python :: 3.7
Classifier: Programming Language :: Python :: 3.8
Classifier: Programming Language :: Python :: 3.9
Requires-Python: >=3.7
License-File: LICENSE
Requires-Dist: requests
Requires-Dist: beautifulsoup4
Requires-Dist: pyee
Requires-Dist: pycookiecheat
Requires-Dist: pydash
Requires-Dist: websocket-client
Requires-Dist: flask
Requires-Dist: flask-session
Requires-Dist: pyotp
Requires-Dist: playwright
Dynamic: license-file
